git_cu/__init__.py
git_cu/main.py
git_cu-0.5.0.dist-info/entry_points.txt
git_cu-0.5.0.dist-info/LICENSE
git_cu-0.5.0.dist-info/WHEEL
git_cu-0.5.0.dist-info/METADATA
git_cu-0.5.0.dist-info/RECORD
