Metadata-Version: 2.1
Name: git-cu
Version: 0.5.0
Summary: git-cu helps keep your local git repositories organized by cloning them into a directory structure based on their URL.
License: GPL-3.0-only
Author: Vasili Revelas
Author-email: vasili.revelas@gmail.com
Requires-Python: >=3.6,<4.0
Classifier: License :: OSI Approved :: GNU General Public License v3 (GPLv3)
Classifier: Programming Language :: Python :: 3
Classifier: Programming Language :: Python :: 3.6
Classifier: Programming Language :: Python :: 3.7
Classifier: Programming Language :: Python :: 3.8
